acached/__init__.py
acached/cache.py
acached-0.1.0.dist-info/LICENSE
acached-0.1.0.dist-info/METADATA
acached-0.1.0.dist-info/WHEEL
acached-0.1.0.dist-info/RECORD
