Metadata-Version: 2.1
Name: acached
Version: 0.1.0
Summary: Cache for syncronous and asyncrounous functions
Author: qwlions
Author-email: qwlions@gmail.com
Requires-Python: >=3.12,<4.0
Classifier: Programming Language :: Python :: 3
Classifier: Programming Language :: Python :: 3.12
Classifier: Programming Language :: Python :: 3.13
